jupytee/__init__.py
jupytee/jupytee.py
jupytee/untitled.py
jupytee-0.0.4.dist-info/LICENSE
jupytee-0.0.4.dist-info/METADATA
jupytee-0.0.4.dist-info/WHEEL
jupytee-0.0.4.dist-info/top_level.txt
jupytee-0.0.4.dist-info/RECORD
