Metadata-Version: 2.1
Name: jupytee
Version: 0.0.4
Summary: Magics for using GPT-like models inside Jupyter.
Author: Fernando Pérez
Author-email: fernando.perez@berkeley.edu
License: BSD 3-Clause License
Keywords: ipython,jupyter,GPT-3,OpenAI
Classifier: Programming Language :: Python :: 3
Classifier: License :: OSI Approved :: BSD License
Classifier: Operating System :: OS Independent
Requires-Python: >=3.7
License-File: LICENSE
